[
  {
    "model": "docs_metadata.companywelcome",
    "pk": 1,
    "fields": {
      "help_command": 5,
      "add_document_command": 1,
      "add_next_document_command": 2,
      "end_document_command": 3,
      "cancel_command": 4,
      "readd_document_text": "Чтобы повторно начать процедуру передачи копий документов \nНажми <b>{ADD_DOCUMENT_COMMAND}</b>",
      "help_text": "<b>Я бот Документооборот, помощник отдела кадров</b> \uD83D\uDCCE\n\nЯ помогу тебе передать документы для оформления сотрудникам кадрового отдела\n\nЕсли ты не захочешь воспользоваться моей помощью в Telegram, то можешь передать документы мне на почту\n<b>zhilo-a@surf.dev</b>\n\nили на нашем сайте\nhttps://staffdoc.surf.dev\n\nДля оформления по ТК РФ потребуются копии следующих документов:\n\uD83D\uDD39Паспорт\n    \uD83D\uDD38вторая и третья страницы\n    \uD83D\uDD38страница с действующей пропиской\n\uD83D\uDD39СНИЛС\n\uD83D\uDD39ИНН\n\uD83D\uDD39Реквизиты карты для ЗП\n\uD83D\uDD39Справки с предыдущего места работы\n    \uD83D\uDD38182Н\n    \uD83D\uDD382НДФЛ\n\uD83D\uDD39Диплом об образовании (высшее/среднее, что есть на руках)\n\uD83D\uDD39Военный билет или приписное свидетельство\n\uD83D\uDD39Свидетельства о рождении детей, если есть\n\uD83D\uDD39Трудовая книжка\n    \uD83D\uDD38если ведется в электронном виде, то необходима справка по форме СТД-Р\n    \uD83D\uDD38если ведется в бумажном виде, то дополнительно, оригинал трудовой книжки необходимо передать в офис компании г. Воронеж",
      "start_text": "<b>Привет!</b>\n{HELP_TEXT}\nЧтобы начать процедуру передачи копий документов \nНажми <b>{ADD_DOCUMENT_COMMAND}</b>"
    }
  }
]
